tests/__init__.py
tknote/__init__.py
tknote/__main__.py
tknote/pyrustic_data/backstage/config/build.json
tknote/pyrustic_data/backstage/config/init.json
tknote/pyrustic_data/backstage/config/release.json
tknote/pyrustic_data/backstage/data/github_release_form.json
tknote/pyrustic_data/backstage/report/build_report.json
tknote/pyrustic_data/backstage/report/release_report.json
tknote/pyrustic_data/hubstore/img.json
tknote/pyrustic_data/hubstore/promotion.json
tknote-0.0.1.dist-info/LICENSE
tknote-0.0.1.dist-info/METADATA
tknote-0.0.1.dist-info/WHEEL
tknote-0.0.1.dist-info/entry_points.txt
tknote-0.0.1.dist-info/top_level.txt
tknote-0.0.1.dist-info/RECORD
